moneypy/__init__.py
moneypy/currencies.py
moneypy/currency.py
moneypy/money.py
money.py-1.0.2.dist-info/LICENSE
money.py-1.0.2.dist-info/METADATA
money.py-1.0.2.dist-info/WHEEL
money.py-1.0.2.dist-info/top_level.txt
money.py-1.0.2.dist-info/RECORD
